CHANGES.rst
MANIFEST.in
README.rst
pyproject.toml
setup.cfg
setup.py
src/mauritstest.namespacepackage.egg-info/PKG-INFO
src/mauritstest.namespacepackage.egg-info/SOURCES.txt
src/mauritstest.namespacepackage.egg-info/dependency_links.txt
src/mauritstest.namespacepackage.egg-info/not-zip-safe
src/mauritstest.namespacepackage.egg-info/top_level.txt
src/mauritstest/namespacepackage/__init__.py