Metadata-Version: 2.4
Name: mauritstest.namespacepackage
Version: 1.0.2
Summary: Test namespace package from Maurits
Home-page: https://github.com/mauritsvanrees/mauritstest.namespacepackage
Author: Maurits van Rees
Author-email: maurits@vanrees.org
License: GPL
Keywords: test release pypi
Classifier: Development Status :: 3 - Alpha
Classifier: Intended Audience :: Developers
Classifier: License :: OSI Approved :: GNU General Public License (GPL)
Classifier: Programming Language :: Python
Classifier: Programming Language :: Python :: 3
Classifier: Programming Language :: Python :: 3.11
Requires-Python: >=3.8
Dynamic: author
Dynamic: author-email
Dynamic: classifier
Dynamic: description
Dynamic: home-page
Dynamic: keywords
Dynamic: license
Dynamic: requires-python
Dynamic: summary
